[ {"Symbol":"NDAQ", "StartDateTime":"06\/15\/2011 09:30:00.000", "EndDateTime":"06\/15\/2011 10:30:00.000", "TWAP":23.9758863328822, "Trades":739, "VWAP":23.9752345156377, "Volume":101102, "Outcome":"Success", "Message":null, "Identity":"Cookie", "Delay":0.0156}, {"Symbol":"GOOG", "StartDateTime":"06\/15\/2011 09:30:00.000", "EndDateTime":"06\/15\/2011 10:30:00.000", "TWAP":506.659011627907, "Trades":1032, "VWAP":506.47296366308, "Volume":135427, "Outcome":"Success", "Message":null, "Identity":null, "Delay":0} ]